otpbot/__init__.py
otpbot/cmds/__init__.py
otpbot/cmds/help.py
otpbot/cmds/start.py
otpbot/constant.py
otpbot/handlers/__init__.py
otpbot/handlers/add.py
otpbot/handlers/cancel.py
otpbot/handlers/delete.py
otpbot/handlers/list.py
otpbot/handlers/show.py
otpbot/handlers/start.py
otpbot/helpers/__init__.py
otpbot/helpers/crypto.py
otpbot/helpers/env.py
otpbot/helpers/keyboards.py
otpbot/helpers/persistence.py
otpbot/main.py
yaotpbot-0.1.0.dist-info/LICENSE
yaotpbot-0.1.0.dist-info/METADATA
yaotpbot-0.1.0.dist-info/WHEEL
yaotpbot-0.1.0.dist-info/entry_points.txt
yaotpbot-0.1.0.dist-info/RECORD
