Metadata-Version: 2.1
Name: yaotpbot
Version: 0.1.0
Summary: A telegram bot to generate OTPs
Home-page: https://github.com/ollaw/yaotpbot
License: MIT
Keywords: telegram-bot,otp
Author: Olla Gabriele
Author-email: dev@ollaw.xyz
Requires-Python: >=3.10,<4.0
Classifier: License :: OSI Approved :: MIT License
Classifier: Programming Language :: Python :: 3
Classifier: Programming Language :: Python :: 3.10
Classifier: Programming Language :: Python :: 3.11
Classifier: Programming Language :: Python :: 3.12
Requires-Dist: boto3 (>=1.24.60,<2.0.0)
Requires-Dist: dynamodb-encryption-sdk (>=3.1.0,<4.0.0)
Requires-Dist: pyotp (>=2.6.0,<3.0.0)
Requires-Dist: python-telegram-bot (>=21.4,<22.0)
Project-URL: Documentation, https://github.com/ollaw/yaotpbot/blob/main/README.md
Project-URL: Repository, https://github.com/ollaw/yaotpbot
